pydantic_optuna_bridge/__init__.py
pydantic_optuna_bridge/__main__.py
pydantic_optuna_bridge/metadata.py
pydantic_optuna_bridge/py.typed
pydantic_optuna_bridge-0.1.1.dist-info/METADATA
pydantic_optuna_bridge-0.1.1.dist-info/WHEEL
pydantic_optuna_bridge-0.1.1.dist-info/licenses/LICENSE
pydantic_optuna_bridge-0.1.1.dist-info/RECORD
