Metadata-Version: 2.4
Name: pydantic-optuna-bridge
Version: 0.1.1
Summary: Derive Optuna distributions from constrained Pydantic models.
Project-URL: Homepage, https://github.com/alexdong/pydantic-optuna-bridge
Project-URL: Repository, https://github.com/alexdong/pydantic-optuna-bridge.git
Author: Alex Dong
License:                                  Apache License
License-File: LICENSE
Keywords: automation,hyperparameter,metadata,optuna,pydantic
Classifier: Development Status :: 3 - Alpha
Classifier: Intended Audience :: Developers
Classifier: License :: OSI Approved :: MIT License
Classifier: Programming Language :: Python
Classifier: Programming Language :: Python :: 3
Classifier: Programming Language :: Python :: 3.12
Classifier: Programming Language :: Python :: 3.13
Classifier: Topic :: Scientific/Engineering :: Artificial Intelligence
Requires-Python: >=3.12
Requires-Dist: annotated-types>=0.6
Requires-Dist: pydantic>=2.6
Provides-Extra: cli
Requires-Dist: click>=8.1; extra == 'cli'
Requires-Dist: loguru>=0.7; extra == 'cli'
Requires-Dist: rich>=13.7; extra == 'cli'
Provides-Extra: default
